cau_utilities/__init__.py
cau_utilities-0.0.4.dist-info/LICENSE.txt
cau_utilities-0.0.4.dist-info/METADATA
cau_utilities-0.0.4.dist-info/WHEEL
cau_utilities-0.0.4.dist-info/top_level.txt
cau_utilities-0.0.4.dist-info/RECORD
